ms_performance_prechecker/__init__.py
ms_performance_prechecker/__main__.py
ms_performance_prechecker/prechecker/__init__.py
ms_performance_prechecker/prechecker/cluster_collector.py
ms_performance_prechecker/prechecker/config_checker.py
ms_performance_prechecker/prechecker/env_checker.py
ms_performance_prechecker/prechecker/env_suggestion.py
ms_performance_prechecker/prechecker/hccl_checker.py
ms_performance_prechecker/prechecker/model_checker.py
ms_performance_prechecker/prechecker/register.py
ms_performance_prechecker/prechecker/system_checker.py
ms_performance_prechecker/prechecker/utils.py
ms_performance_prechecker/prechecker/hardware_capacity/__init__.py
ms_performance_prechecker/prechecker/hardware_capacity/cpu_checker.py
ms_performance_prechecker/prechecker/hardware_capacity/npu_checker.py
ms_performance_prechecker/prechecker/hardware_capacity/time_analyze.py
ms_performance_prechecker-0.0.1a16.dist-info/METADATA
ms_performance_prechecker-0.0.1a16.dist-info/WHEEL
ms_performance_prechecker-0.0.1a16.dist-info/entry_points.txt
ms_performance_prechecker-0.0.1a16.dist-info/top_level.txt
ms_performance_prechecker-0.0.1a16.dist-info/RECORD
