Metadata-Version: 2.1
Name: ms-performance-prechecker
Version: 0.0.1a16
Summary: MindStudio Performance Prechecker
License: Apache-2.0
Project-URL: source, https://gitee.com/ascend/msit/tree/msserviceprofiler_dev/ms_performance_prechecker
Project-URL: documentation, https://gitee.com/ascend/msit/tree/msserviceprofiler_dev/ms_performance_prechecker
Project-URL: tracker, https://gitee.com/ascend/msit/issues
Keywords: ms,performance,prechecker
Classifier: Programming Language :: Python :: 3
Classifier: Programming Language :: Python :: 3.8
Classifier: Programming Language :: Python :: 3.9
Classifier: Programming Language :: Python :: 3.10
Classifier: Programming Language :: Python :: 3.11
Classifier: License :: OSI Approved :: Apache Software License
Classifier: Operating System :: OS Independent
Requires-Python: >=3.8
